degiroapi/__init__.py
degiroapi/client_info.py
degiroapi/datatypes.py
degiroapi/intervaltypes.py
degiroapi/order.py
degiroapi/product.py
degiroapi/utils.py
degiroapi-0.9.5.dist-info/LICENSE
degiroapi-0.9.5.dist-info/METADATA
degiroapi-0.9.5.dist-info/WHEEL
degiroapi-0.9.5.dist-info/top_level.txt
degiroapi-0.9.5.dist-info/RECORD
