Metadata-Version: 2.1
Name: degiroapi
Version: 0.9.5
Summary: An unofficial API for the trading platform Degiro written in Python
Home-page: https://github.com/lolokraus/DegiroAPI
Author: Lorenz Kraus
Author-email: lorenz.kraus@gmail.com
License: UNKNOWN
Platform: UNKNOWN
Classifier: Programming Language :: Python :: 3
Classifier: License :: OSI Approved :: MIT License
Classifier: Operating System :: OS Independent
Requires-Python: >=3.6
